HumanReadableSeed/HumanReadableSeed.py
HumanReadableSeed/__init__.py
HumanReadableSeed/__main__.py
humanreadableseed-0.0.10.dist-info/licenses/LICENSE
humanreadableseed-0.0.10.dist-info/METADATA
humanreadableseed-0.0.10.dist-info/WHEEL
humanreadableseed-0.0.10.dist-info/entry_points.txt
humanreadableseed-0.0.10.dist-info/top_level.txt
humanreadableseed-0.0.10.dist-info/RECORD
