Metadata-Version: 2.4
Name: HumanReadableSeed
Version: 0.0.10
Summary: Reversible conversion between seeds and human readable words
Home-page: https://github.com/thiswillbeyourgithub/HumanReadableSeed
Keywords: seeds,crypto,bitcoin,bip39,readable,seed,wordlist,nltk,onetime,pad,token,mnemonic
Classifier: Programming Language :: Python :: 3
Classifier: Operating System :: OS Independent
Requires-Python: >=3.11
License-File: LICENSE
Requires-Dist: fire
Requires-Dist: nltk
Dynamic: classifier
Dynamic: description
Dynamic: description-content-type
Dynamic: home-page
Dynamic: keywords
Dynamic: license-file
Dynamic: requires-dist
Dynamic: requires-python
Dynamic: summary
